kivyir/ConfigBase.py
kivyir/IrLabel.py
kivyir/IrTextInput.py
kivyir/__init__.py
kivyir/font/Sahel-Bold.ttf
kivyir/font/Sahel.ttf
test/main.py
kivyir-0.1.5.dist-info/LICENSE
kivyir-0.1.5.dist-info/METADATA
kivyir-0.1.5.dist-info/WHEEL
kivyir-0.1.5.dist-info/top_level.txt
kivyir-0.1.5.dist-info/RECORD
