Metadata-Version: 2.1
Name: kivyir
Version: 0.1.5
Summary: Improving the display of Persian text for Persian speakers
Home-page: https://github.com/goldaaa/kivyir
Download-URL: https://github.com/goldaaa/kivyir/tarball/master
Author: navid nasiri
Author-email: goldaaa.program@gmail.com
Maintainer: navid nasiri
Maintainer-email: goldaaa.program@gmail.com
License: MIT
Keywords: kivy persian farsi iran
Platform: ALL
Classifier: License :: OSI Approved :: MIT License
Classifier: Intended Audience :: Developers
Classifier: Natural Language :: Persian
Classifier: Programming Language :: Python
Classifier: Programming Language :: Python :: 2.7
Classifier: Programming Language :: Python :: 3.5
Classifier: Programming Language :: Python :: 3.6
Classifier: Programming Language :: Python :: 3.7
Classifier: Programming Language :: Python :: 3.8
Classifier: Programming Language :: Python :: 3.9
Classifier: Programming Language :: Python :: 3.10
Classifier: Topic :: Software Development :: User Interfaces
Classifier: Topic :: Software Development :: Libraries :: Python Modules
Requires-Python: >=3.5
License-File: LICENSE
Requires-Dist: kivy (>=2.0.0)
Requires-Dist: pillow
Requires-Dist: facleaning
